app/__init__.py
app/server.py
devops_container_image_code_generator/chains/__init__.py
devops_container_image_code_generator/chains/container_image_code_generator_chain.py
devops_container_image_code_generator/chains/container_image_code_generator_chain_application_service.py
devops_container_image_code_generator/chains/container_image_code_generator_chain_for_middleware.py
devops_container_image_code_generator/chains/container_image_code_generator_chain_resource.py
devops_container_image_code_generator/templates/container_image_code/java/apache_maven/apache_tomcat/Dockerfile.template
devops_container_image_code_generator/templates/container_image_code/java/apache_maven/spring_boot_version_2.3.0_and_above/Dockerfile.template
devops_container_image_code_generator/templates/container_image_code/java/apache_maven/spring_boot_version_2.3.0_and_above/entrypoint_script.template
devops_container_image_code_generator/templates/container_image_code/java/apache_maven/spring_boot_version_less_than_2.3.0/Dockerfile.template
devops_container_image_code_generator/templates/container_image_code/java/apache_maven/spring_boot_version_less_than_2.3.0/entrypoint_script.template
devops_container_image_code_generator/templates/container_image_code/python/poetry/langserve/Dockerfile.template
devops_container_image_code_generator/templates/container_image_code/python/poetry/langserve/entrypoint_script.template
devops_container_image_code_generator/templates/container_image_code/python/poetry/langserve/prompt_append.txt
devops_container_image_code_generator-1.20240710.5.dist-info/LICENSE
devops_container_image_code_generator-1.20240710.5.dist-info/METADATA
devops_container_image_code_generator-1.20240710.5.dist-info/WHEEL
devops_container_image_code_generator-1.20240710.5.dist-info/RECORD
