Metadata-Version: 2.1
Name: devops-container-image-code-generator
Version: 1.20240710.5
Summary: GenAI Application which uses Langchain and source code repository files, such as dependency manifests, to generate container image code like Dockerfile and entrypoint script.
Home-page: https://github.com/devopscodegen/devops-container-image-code-generator
License: MIT
Keywords: devops,container-image-code-generator,devops-platform,langchain,genai
Author: Sagar Velankar
Author-email: sagar.velankar@gmail.com
Requires-Python: >=3.11,<4.0
Classifier: Development Status :: 1 - Planning
Classifier: Intended Audience :: Developers
Classifier: License :: OSI Approved :: MIT License
Classifier: Operating System :: OS Independent
Classifier: Programming Language :: Python :: 3
Classifier: Programming Language :: Python :: 3.11
Classifier: Programming Language :: Python :: 3.12
Classifier: Topic :: Software Development :: Code Generators
Requires-Dist: devopscodegen-common (>=1.20240710.1,<2.0.0)
Requires-Dist: langchain-core (>=0.1.5,<0.3)
Requires-Dist: langchain-openai (>=0.0.1)
Requires-Dist: langserve[server] (>=0.0.30)
Requires-Dist: opentelemetry-distro (>=0.46b0,<0.47)
Requires-Dist: opentelemetry-exporter-otlp (>=1.25.0,<2.0.0)
Requires-Dist: opentelemetry-instrumentation-asyncio (>=0.46b0,<0.47)
Requires-Dist: opentelemetry-instrumentation-aws-lambda (>=0.46b0,<0.47)
Requires-Dist: opentelemetry-instrumentation-dbapi (>=0.46b0,<0.47)
Requires-Dist: opentelemetry-instrumentation-fastapi (>=0.46b0,<0.47)
Requires-Dist: opentelemetry-instrumentation-grpc (>=0.46b0,<0.47)
Requires-Dist: opentelemetry-instrumentation-httpx (>=0.46b0,<0.47)
Requires-Dist: opentelemetry-instrumentation-logging (>=0.46b0,<0.47)
Requires-Dist: opentelemetry-instrumentation-requests (>=0.46b0,<0.47)
Requires-Dist: opentelemetry-instrumentation-sqlite3 (>=0.46b0,<0.47)
Requires-Dist: opentelemetry-instrumentation-threading (>=0.46b0,<0.47)
Requires-Dist: opentelemetry-instrumentation-tortoiseorm (>=0.46b0,<0.47)
Requires-Dist: opentelemetry-instrumentation-urllib (>=0.46b0,<0.47)
Requires-Dist: opentelemetry-instrumentation-urllib3 (>=0.46b0,<0.47)
Requires-Dist: opentelemetry-instrumentation-wsgi (>=0.46b0,<0.47)
Requires-Dist: uvicorn (>=0.23.2,<0.24.0)
Project-URL: Documentation, https://github.com/devopscodegen/devops-container-image-code-generator
Project-URL: Repository, https://github.com/devopscodegen/devops-container-image-code-generator
